urgent/__init__.py
urgent/ast.py
urgent/cli.py
urgent/codegen.py
urgent/compiler.py
urgent/config.py
urgent/expr_parser_gen.py
urgent/parser_gen.py
urgent/parser_wrap.py
urgent/repl1s.py
urgent/repl_parser_gen.py
urgent/repl_parser_wrap.py
urgent/scope.py
urgent-0.1.2.dist-info/LICENSE
urgent-0.1.2.dist-info/METADATA
urgent-0.1.2.dist-info/WHEEL
urgent-0.1.2.dist-info/entry_points.txt
urgent-0.1.2.dist-info/top_level.txt
urgent-0.1.2.dist-info/RECORD
