Metadata-Version: 2.1
Name: urgent
Version: 0.1.2
Summary: UNKNOWN
Home-page: https://github.com/RemuLang/urgent
Author: thautawarm
Author-email: twshere@outlook.com
License: mit
Platform: any
Classifier: Programming Language :: Python :: 3.6
Classifier: Programming Language :: Python :: 3.7
Classifier: Programming Language :: Python :: Implementation :: CPython
Requires-Python: >=3.6.0
Requires-Dist: rbnf-rts
Requires-Dist: toml
Requires-Dist: argser
Requires-Dist: sijuiacion-lang
Requires-Dist: remu-operator
